rnode-0.2.9.dist-info/METADATA
rnode-0.2.9.dist-info/WHEEL
rnode.libs/libcrypto-b24afd48.so.3
rnode.libs/libssl-57118d4e.so.3
rnode/tests/__init__.py
rnode/tests/test_market_data.py
rnode/tests/quick_test.py
rnode/tests/ws_echo_test.py
rnode/tests/ws_test.py
rnode/tests/example.py
rnode/tests/node_test.py
rnode/tests/replay.py
rnode/tests/resample.py
rnode/types.py
rnode/__init__.py
rnode/interface.py
rnode/rnode.cpython-311-x86_64-linux-gnu.so
rnode-0.2.9.dist-info/RECORD
