Metadata-Version: 2.4
Name: rnode
Version: 0.2.9
Requires-Dist: maturin >=1.0.0 ; extra == 'dev'
Provides-Extra: dev
Summary: Market data service Python bindings
Author-email: stark <ywiscat@gmail.com>
Requires-Python: >=3.11
